{"forum": {"content": "\u7b2c\u4e00\u6b21\u5750\u90f5\u8f2a", "images": ["http://filestoresg1.beetalkmobile.com:8081/file/f2eef62aca4538ec7a78d581dc00f836", "http://filestoresg1.beetalkmobile.com:8081/file/1c2b68062830acc9fd81b81a4565f9ab", "http://filestoresg1.beetalkmobile.com:8081/file/ff9d1cb328b1e2d1428d7f79a09f1f08", "http://filestoresg1.beetalkmobile.com:8081/file/8204ec982e7e55a85a82c75c370f66b2", "http://filestoresg1.beetalkmobile.com:8081/file/f7610b90081e97246befdb2f3751adc9", "http://filestoresg1.beetalkmobile.com:8081/file/a3f660e2170f2ae6343e91515bd979c8"], "urls": [], "title": "Costa \u904a\u8f2a"}, "threadStatus": 0, "regionId": 886, "barStatus": 0, "barId": 85, "postBy": {"utc": 1423206547000, "level": 3, "location": "\u53f0\u4e2d\u5e02\u00b7\u53f0\u7063", "avatar": "http://filestoresg1.beetalkmobile.com:8081/file/4627478304846446851", "name": "steven"}, "id": 433627}
