{"forum": {"content": "\u5927\u5bb6\u4e00\u8d77\u804a\u804a\u5929~~<br />\u52a0\u52a0\u597d\u53cb\u5427~~><<br />\u5e0c\u671b\u5927\u5bb6\u90fd\u80fd\u6210\u70ba\u670b\u53cb!!!!^\u76bf^", "images": ["http://filestoresg1.beetalkmobile.com:8081/file/70bd0458da23903b427039c50d9d1307", "http://filestoresg1.beetalkmobile.com:8081/file/2e6805dc40a9da1ae6380551bea425ee", "http://filestoresg1.beetalkmobile.com:8081/file/12479460996cbccf28d2c60fa27dd7eb", "http://filestoresg1.beetalkmobile.com:8081/file/90b4d8de6ddf6ad911dfb59d16a79e2e"], "urls": [], "title": "\u9ad8\u4e8c~~"}, "threadStatus": 1, "regionId": 886, "barStatus": 0, "barId": 438, "postBy": {"utc": 1424950865000, "level": 1, "location": "\u65b0\u5317\u5e02\u00b7\u53f0\u7063", "avatar": "http://filestoresg1.beetalkmobile.com:8081/file/-681597151391970560", "name": "Ting Yang"}, "id": 607579}
