{"forum": {"content": "\u81ea\u5df1\u4e26\u4e0d\u7f8e\uff0c\u52aa\u529b\u81ea\u4fe1\uff0c\u8b93\u81ea\u5df1\u66f4\u7f8e<br /><br />\u60f3\u591a\u4ea4\u670b\u53cb\u5466\uff5e<br />fb:\u7ae5\u66c9\u827e", "images": ["http://filestoresg1.beetalkmobile.com:8081/file/6a20b3e59fd466ac8d1d196cc91f1582", "http://filestoresg1.beetalkmobile.com:8081/file/a5244ca6e898fcee19fc10120dbdca4d", "http://filestoresg1.beetalkmobile.com:8081/file/c80a30d0edb7e40e9e2387f8089278c0", "http://filestoresg1.beetalkmobile.com:8081/file/ce6a7b9c96d3e8de53fe7e0f22c5cc32", "http://filestoresg1.beetalkmobile.com:8081/file/06bb45d21765c97df71d42d4aa9f0207", "http://filestoresg1.beetalkmobile.com:8081/file/f8cda83fcb2262e758702e6eaa65f5a6"], "urls": [], "title": "\u5927\u5bb6\u90fd\u597d\u7f8e\u5466\uff5e"}, "threadStatus": 0, "regionId": 886, "barStatus": 0, "barId": 32, "postBy": {"utc": 1423608296000, "level": 2, "location": "\u65b0\u5317\u5e02\u00b7\u53f0\u7063", "avatar": "http://filestoresg1.beetalkmobile.com:8081/file/5735496861933891069", "name": "\u516c\u95dc\u827e\u827e"}, "id": 469622}
