{"forum": {"content": "\u55e8\ud83d\ude02", "images": ["http://filestoresg1.beetalkmobile.com:8081/file/4baf07a23ca81571e47b1c3cc603ba3c", "http://filestoresg1.beetalkmobile.com:8081/file/47e84337dd162f819791efe52e765b07", "http://filestoresg1.beetalkmobile.com:8081/file/9a6b6dd95806485125b9e6397022f3a9", "http://filestoresg1.beetalkmobile.com:8081/file/f2c15c23ba584399b389e5a45943f67e"], "urls": [], "title": "\u55e8\u55e8\ud83d\ude01"}, "threadStatus": 1, "regionId": 886, "barStatus": 0, "barId": 4, "postBy": {"utc": 1427606995000, "level": 2, "location": "\u96f2\u6797\u7e23\u00b7\u53f0\u7063", "avatar": "http://filestoresg1.beetalkmobile.com:8081/file/-3960233074162870516", "name": "\u4f7f\u7528\u8005"}, "id": 884249}
