{"forum": {"content": "\u534a\u591cpo\u7f8e\u98df<br />\u662f\u4e0d\u662f\u8981\u4f86\u9760\u5317\u4e00\u4e0b<br />", "images": ["http://filestoresg1.beetalkmobile.com:8081/file/5a98705e9b97dad2329b04f4e730b582", "http://filestoresg1.beetalkmobile.com:8081/file/945d220861d619badca2c6aa80882089", "http://filestoresg1.beetalkmobile.com:8081/file/50ccac4be8286885d588193b09bcc30f"], "urls": [], "title": "\u6211\u597d\u9913"}, "threadStatus": 1, "regionId": 886, "barStatus": 0, "barId": 391, "postBy": {"utc": 1424628949000, "level": 4, "location": "\u65b0\u5317\u5e02\u00b7\u53f0\u7063", "avatar": "http://filestoresg1.beetalkmobile.com:8081/file/8710253054339703517", "name": "\ud83d\udc41\ud83d\udc41"}, "id": 572655}
