{"forum": {"content": "\u53c8\u662f\u9a0e\u4eba\u52ab\u800c\u4e14\u9084\u662f\u767d\u5c04\u9a0e\u4eba\u52ab<br />\u4f86\u7559\u8a00\u544a\u8a34\u6211\u4eca\u5929\u4f60/\u59b3\u600e\u9ebc\u904e?<br />", "images": ["http://filestoresg1.beetalkmobile.com:8081/file/3f82715cace2b09c72cf3af81747d1b4"], "urls": [], "title": "0314"}, "threadStatus": 1, "regionId": 886, "barStatus": 0, "barId": 32, "postBy": {"utc": 1426270459000, "level": 6, "location": "\u6843\u5712\u5e02\u00b7\u53f0\u7063", "avatar": "http://filestoresg1.beetalkmobile.com:8081/file/-6111806904989240231", "name": "0"}, "id": 750270}
