{"forum": {"content": "\u80fd\u4e0d\u80fd\u5728\u4eca\u5e74\u628a\u81ea\u5df1\u63a8\u92b7\u51fa\u53bb\uff0c\u559c\u6b61\u6211\u53ef\u4ee5\u52a0\u6211", "images": ["http://filestoresg1.beetalkmobile.com:8081/file/c20d34371a427b34d94effa809d6e006"], "urls": [], "title": "\u55ae\u8eab\u597d\u4e45\uff0c\u597d\u5b64\u55ae"}, "threadStatus": 0, "regionId": 886, "barStatus": 0, "barId": 205, "postBy": {"utc": 1418412229000, "level": 1, "location": "\u5b9c\u862d\u7e23\u00b7\u53f0\u7063", "avatar": "http://filestoresg1.beetalkmobile.com:8081/file/4847603832204635148", "name": "\u963f\u820d"}, "id": 73150}
