{"forum": {"content": "\u807d\u4f60\u5bc2\u5bde\u5728\u5531\u6b4c<br />", "images": [], "urls": [{"url": "http://youtu.be/0F1vGjJgTU0", "thumbUrl": "http://i.ytimg.com/vi/0F1vGjJgTU0/maxresdefault.jpg", "description": "\u9748\u9b42\u5bb6\u5bb6\u3008\u70ba\u4f60\u7684\u5bc2\u5bde\u5531\u6b4c\u3009 12/31\u6b63\u5f0f\u767c\u884c 12/25-27\u96fb\u53f0\u9996\u64ad 12/27\u6578\u4f4d\u97f3\u6a02\u4e0a\u67b6 \u5982\u679c\u5728\u51ac\u591c\u4e00\u500b\u65c5\u4eba,\u8ab0\u70ba\u4f60\u7684\u5bd2\u5fc3\u9ede\u71c8? \u5982\u679c\u5728\u51ac\u591c\u4e00\u500b\u5973\u4eba,\u8ab0\u70ba\u4f60\u7684\u5bc2\u5bde\u9ede\u6b4c? \u5982\u679c\u5728\u51ac\u591c,\u516b\u65b9\u5bc2\u5bde\u90fd", "title": "JiaJia\u5bb6\u5bb6[\u70ba\u4f60\u7684\u5bc2\u5bde\u5531\u6b4cSing For Lonely Souls] \u5b8c\u6574\u7248\u97f3\u6a94Lyrics Video"}], "title": "\u5bb6\u5bb6"}, "threadStatus": 0, "regionId": 886, "barStatus": 0, "barId": 54, "postBy": {"utc": 1416471982000, "level": 2, "location": "", "avatar": "http://filestoresg1.beetalkmobile.com:8081/file/-7386036423167701860", "name": "\u547d\u904b"}, "id": 24073}
