{"forum": {"content": "NG\u6b61\u6a02\u5834\u55b2<br />1\u7f3a4\u5feb\u4f86\u5440\uff01", "images": ["http://filestoresg1.beetalkmobile.com:8081/file/b11024938a720952fec17a002d897599"], "urls": [], "title": "NG\u6b61\u6a02\u5834\u55b2  1\u7f3a4  \u6709mic\u4f73"}, "threadStatus": 1, "regionId": 886, "barStatus": 0, "barId": 60, "postBy": {"utc": 1422361037000, "level": 4, "location": "\u53f0\u5357\u5e02\u00b7\u53f0\u7063", "avatar": "http://filestoresg1.beetalkmobile.com:8081/file/-8051814901317085911", "name": " \u337f"}, "id": 366786}
