{"forum": {"content": "\ud83d\ude0e\ud83d\ude24", "images": [], "urls": [{"url": "https://m.youtube.com/watch?sts=16407&utcoffset=480&v=yiK9Hnxlgrk&oref=https%3A%2F%2Fm.youtube.com%2Fwatch%3Fv%3DyiK9Hnxlgrk%26itct%3DCE0QpDAYACITCOOMhOjnscICFY1oWAodBqkAw1IIbWFzdGEgd3U%253D&has_verified=1&layout=mobile&client=mv-google", "thumbUrl": "https://i.ytimg.com/vi/yiK9Hnxlgrk/maxresdefault.jpg", "description": "[MASTA WU \u2013 '\uc774\ub9ac\uc640\ubd10(COME HERE)' (feat. Dok2, BOBBY) M/V] Download on iTunes @ http://smarturl.it/MASTA", "title": "MASTA WU \u2013 '\uc774\ub9ac\uc640\ubd10(COME HERE)' (feat. Dok2, BOBBY) M/V"}], "title": "Come here\ud83d\udc4d"}, "threadStatus": 0, "regionId": 886, "barStatus": 0, "barId": 54, "postBy": {"utc": 1417882609000, "level": 1, "location": "\u9ad8\u96c4\u5e02\u00b7\u53f0\u7063", "avatar": "http://filestoresg1.beetalkmobile.com:8081/file/1638515320425542146", "name": "XIN"}, "id": 44865}
