{"forum": {"content": "\u96d6\u7136\u6211\u6c92\u4ea4\u5973\u670b\u53cb\u4f46\u6211\u689d\u4ef6\u53c8\u4e0d\u5dee<br />\u59b3\u5077\u5403\u9084\u6562\u56de\u4f86\u627e\u6211<br />\u771f\u4e0d\u8981\u81c9 \u771f\u7684\u89ba\u5f97\u59b3\u9ad2<br />\u4e0d\u61c2\u5f97\u5c0a\u91cd\u5225\u4eba\u8ab0\u5c0a\u91cd\u59b3", "images": ["http://filestoresg1.beetalkmobile.com:8081/file/997a8495ef413aac2ab1ac651a8b482d"], "urls": [], "title": "\u771f\u626f"}, "threadStatus": 1, "regionId": 886, "barStatus": 0, "barId": 18, "postBy": {"utc": 1425917458000, "level": 8, "location": "", "avatar": "http://filestoresg1.beetalkmobile.com:8081/file/2723066994309722381", "name": "Shina JN"}, "id": 713476}
