{"forum": {"content": "\u600e\u9ebc\u4ea4\u5973\u670b\u53cb\u554a\uff5e", "images": ["http://filestoresg1.beetalkmobile.com:8081/file/ac225bdd7598fb5520081ad12df01e96", "http://filestoresg1.beetalkmobile.com:8081/file/40563b693e208c95d7c2fa95dc1beb6d"], "urls": [], "title": "\u55ae\u8eab\u7684\u6211"}, "threadStatus": 1, "regionId": 886, "barStatus": 0, "barId": 205, "postBy": {"utc": 1416318864000, "level": 3, "location": "\u53f0\u5357\u5e02\u00b7\u53f0\u7063", "avatar": "http://filestoresg1.beetalkmobile.com:8081/file/7663544369551794177", "name": "\u5c0f\u77ee\u5b50"}, "id": 22200}
