{"forum": {"content": "\u60f3\u8acb\u554f\u5927\u5bb6<br />\u6709\u4e86\u7537\u670b\u53cb<br />\u9084\u662f\u6703\u60f3\u8981\u5225\u7684\u7537\u4eba\u7684\u8eab\u9ad4\u55ce\uff1f<br />\u70ba\u4ec0\u9ebc\uff1f<br />\u5c31\u8ddf\u7537\u751f\u4e00\u6a23\uff01<br />\u6709\u5973\u670b\u53cb\u4e5f\u6703\u60f3\u8457\u5225\u4eba\u7684\u8eab\u9ad4\u4e00\u6a23\uff01", "images": ["http://filestoresg1.beetalkmobile.com:8081/file/aa659d02b82d6300aa55dbdd128a02d1"], "urls": [], "title": "\u7537\u670b\u53cb\u9084\u662f\u5225\u4eba"}, "threadStatus": 1, "regionId": 886, "barStatus": 2, "barId": 5, "postBy": {"utc": 1425810823000, "level": 2, "location": "\u65b0\u5317\u5e02\u00b7\u53f0\u7063", "avatar": "http://filestoresg1.beetalkmobile.com:8081/file/605969446035861249", "name": "\u5a1c\u5a1c"}, "id": 701222}
