{"forum": {"content": "\u975e\u5e38\u6c92\u81ea\u4fe1\u7684\u6211\u3002\u3002\u3002", "images": ["http://filestoresg1.beetalkmobile.com:8081/file/78086851a58470b0023c9f2150c1d291", "http://filestoresg1.beetalkmobile.com:8081/file/fd7d856dcb5b5bf3f2baf11cc9bc62ce", "http://filestoresg1.beetalkmobile.com:8081/file/2186c0f513c78bdceb92958921fa6a5e", "http://filestoresg1.beetalkmobile.com:8081/file/7136814e6fca64b41c4255bc264a6a84", "http://filestoresg1.beetalkmobile.com:8081/file/6cdd0e1a7b60919f8ec2913823ae863d", "http://filestoresg1.beetalkmobile.com:8081/file/4de9b2157db4399fde3478ca1e76fd0d"], "urls": [], "title": "\u8a0e\u53ad\u7684\u60c5\u4eba\u7bc0\u3002\u3002"}, "threadStatus": 1, "regionId": 886, "barStatus": 0, "barId": 4, "postBy": {"utc": 1426305545000, "level": 6, "location": "\u9ad8\u96c4\u5e02\u00b7\u53f0\u7063", "avatar": "http://filestoresg1.beetalkmobile.com:8081/file/7830150068138939459", "name": "\u8ff7\u5931\u7684\u5f64\u5152"}, "id": 752602}
