{"forum": {"content": "Polaroid Cube \u958b\u7bb1\u6e2c\u8a66\uff0c\u60f3\u8cb7\u904b\u52d5\u76f8\u6a5f\u7684\u4eba\u53ef\u4ee5\u53c3\u8003\u770b\u770b\u5594", "images": [], "urls": [{"url": "http://genkiboy83.pixnet.net/blog/post/42084914", "thumbUrl": "http://pic.pimg.tw/genkiboy83/1426666660-4041277476_n.jpg", "description": "\u81ea\u5f9e GoPro \u5e36\u8d77\u4e86\u4e00\u9663\u6975\u9650\u904b\u52d5\u651d\u5f71\u98a8\u6f6e\u4e4b\u5f8c\uff0cGoPro \u5e7e\u4e4e\u7b49\u65bc\u904b\u52d5\u651d\u5f71\u6a5f\u7684\u4ee3\u540d\u8a5e\uff0c\u76f8\u7576\u521d\u5728\u73a9\u751f\u5b58\u904a\u6232\u7684\u6642\u5019\uff0c\u6574\u968a\u88e1\u9762\u6709\u5927\u6982\u56db\u4e94\u500b\u4eba\u4e0b\u5834\u90fd\u6703\u639b\u8457 GoPro \u4e0b\u5834\uff0c\u975e\u5e38\u8c6a\u83ef\u7684\u968a\u4f0d\u7d44\u5408XD\uff0c \u539f\u672c", "title": "[\u958b\u7bb1] \u5bf6\u9e97\u840a Polaroid Cube \u8ff7\u4f60\u904b\u52d5\u651d\u5f71\u6a5f/\u76f8\u6a5f @ \u5982\u679c\u8a18\u61b6\u50cf\u98a8=\u751f\u6d3b+\u65c5\u884c+\u68d2\u7403+\u651d\u5f71+\u69cd\u8ff7+3C\u963f\u5b85=\u6211\u7684\u4e16\u754c :: \u75de\u5ba2\u90a6 PIXNET ::"}], "title": "Polaroid Cube \u958b\u7bb1\u6e2c\u8a66"}, "threadStatus": 0, "regionId": 886, "barStatus": 0, "barId": 77, "postBy": {"utc": 1426745628000, "level": 6, "location": "\u53f0\u5317\u5e02\u00b7\u53f0\u7063", "avatar": "http://filestoresg1.beetalkmobile.com:8081/file/6297006448294317826", "name": "Richard"}, "id": 797686}
