{"forum": {"content": "\u53ea\u662f\u89ba\u5f97\u7121\u804a\uff0c\u60f3\u627e\u4eba\u804a\u5929\uff0c\u9019\u6a23(\uffe3\u2207\uffe3)", "images": ["http://filestoresg1.beetalkmobile.com:8081/file/5eb829a726c89340616c4051052b78ba"], "urls": [], "title": "\u6c9218\u5716\uff0c\u9084\u6703\u6709\u4eba\u52a0\u55ce\uff1f"}, "threadStatus": 1, "regionId": 886, "barStatus": 2, "barId": 5, "postBy": {"utc": 1425037728000, "level": 7, "location": "\u6843\u5712\u5e02\u00b7\u53f0\u7063", "avatar": "http://filestoresg1.beetalkmobile.com:8081/file/450840453221561420", "name": "\u7d2b"}, "id": 617343}
