{"forum": {"content": "\u9732\u817f\u54c8\u54c8\u54c8", "images": ["http://filestoresg1.beetalkmobile.com:8081/file/121ccb4136d3abd0019da0bf35198e3f"], "urls": [], "title": "\u5225\u5728\u9732\u5976\u4e86\uff01"}, "threadStatus": 1, "regionId": 886, "barStatus": 0, "barId": 4, "postBy": {"utc": 1417444871000, "level": 3, "location": "\u53f0\u5357\u5e02\u00b7\u53f0\u7063", "avatar": "http://filestoresg1.beetalkmobile.com:8081/file/8695031411995096580", "name": "\u26ab\ufe0f\u26ab\ufe0f\u26ab\ufe0f"}, "id": 37454}
