{"forum": {"content": "\uff01\uff01\uff01", "images": ["http://filestoresg1.beetalkmobile.com:8081/file/9021462cb48ef1daad900f16d717ba41", "http://filestoresg1.beetalkmobile.com:8081/file/20ac49f8af70e249edef0c3f780f5e42"], "urls": [], "title": "HI "}, "threadStatus": 0, "regionId": 886, "barStatus": 0, "barId": 4, "postBy": {"utc": 1415151797000, "level": 8, "location": "\u53f0\u7063", "avatar": "http://filestoresg1.beetalkmobile.com:8081/file/1366368602419626326", "name": "\u563f\ud83d\udc4d"}, "id": 7992}
