{"forum": {"content": "\u9577\u8896\u4e0a\u8eab\uff5e", "images": ["http://filestoresg1.beetalkmobile.com:8081/file/93708b37eb5d97565c82b5eb1fd8002e", "http://filestoresg1.beetalkmobile.com:8081/file/a4b08ecce083ff77853d045b8f3b4d85"], "urls": [], "title": "\u5929\u6c23\u7d42\u65bc\u6dbc\u4e86"}, "threadStatus": 0, "regionId": 886, "barStatus": 0, "barId": 32, "postBy": {"utc": 1426917676000, "level": 7, "location": "", "avatar": "http://filestoresg1.beetalkmobile.com:8081/file/1252919894907961089", "name": "Louise Chang"}, "id": 814942}
