{"forum": {"content": "\u6211\u9577\u7684\u4e0d\u8a0e\u559c\u55ce \u90fd\u6c92\u4eba\u559c\u6b61", "images": ["http://filestoresg1.beetalkmobile.com:8081/file/57058fdeee7044a13c9173a05534d0bd", "http://filestoresg1.beetalkmobile.com:8081/file/3c44cc6221ef8b049addf5ca8c8425ed", "http://filestoresg1.beetalkmobile.com:8081/file/cefc0fddba9426f5bc260ccf6266c794"], "urls": [], "title": "\u54ce\u54ce"}, "threadStatus": 1, "regionId": 886, "barStatus": 0, "barId": 33, "postBy": {"utc": 1426917381000, "level": 2, "location": "\u65b0\u5317\u5e02\u00b7\u53f0\u7063", "avatar": "http://filestoresg1.beetalkmobile.com:8081/file/-1935276803028132864", "name": "\u9a5a\u6b4e"}, "id": 814908}
