{"forum": {"content": "\u9019\u4e0d\u662f\u6211\u60f3\u8981\u7684", "images": ["http://filestoresg1.beetalkmobile.com:8081/file/efb57614b94af00c13dd384b830e8b06", "http://filestoresg1.beetalkmobile.com:8081/file/c55176a080d5c5c4fb331b2b6fccdf60"], "urls": [], "title": "\u8f49\u8b8a"}, "threadStatus": 0, "regionId": 886, "barStatus": 0, "barId": 77, "postBy": {"utc": 1428771282000, "level": 2, "location": "", "avatar": "http://filestoresg1.beetalkmobile.com:8081/file/160823368970776345", "name": "\ud83d\udc9e \u5fc3\u5152 \ud83d\udc9e"}, "id": 997340}
