{"forum": {"content": "\u540c\u5fd7\u5708\u670b\u53cb\u592a\u5c11\uff5e\uff5e\uff5e", "images": ["http://filestoresg1.beetalkmobile.com:8081/file/6194c07b6c092cf9d2b49c99fba0c62d", "http://filestoresg1.beetalkmobile.com:8081/file/d67f062fb2679aa10e6f988112e97fae", "http://filestoresg1.beetalkmobile.com:8081/file/44be7624b142429fdfa8f2f19ff8b826", "http://filestoresg1.beetalkmobile.com:8081/file/de6d1bd4b625c4a32478db0e42a988c2", "http://filestoresg1.beetalkmobile.com:8081/file/7ec0c5ff37fe7fd37fb96c3eeee1fd5b", "http://filestoresg1.beetalkmobile.com:8081/file/7e29ea5cafc5b82292d016e0facd1a1b"], "urls": [], "title": "\u5fb5\u53cb\uff08\u4ffa\u662fT\uff09"}, "threadStatus": 0, "regionId": 886, "barStatus": 0, "barId": 20, "postBy": {"utc": 1428734630000, "level": 1, "location": "\u53f0\u5317\u5e02\u00b7\u53f0\u7063", "avatar": "http://filestoresg1.beetalkmobile.com:8081/file/-6265603285858900220", "name": "\u5947\u7570\u679c"}, "id": 993005}
