{"forum": {"content": "\u737b\u919c", "images": ["http://filestoresg1.beetalkmobile.com:8081/file/1a237351e41b708f07fc1320d56e6c74", "http://filestoresg1.beetalkmobile.com:8081/file/42225c4d69cffe8d5d23b25ab8598b14", "http://filestoresg1.beetalkmobile.com:8081/file/cffa529fdc45f78519817527792d7751", "http://filestoresg1.beetalkmobile.com:8081/file/fb249af7100eb1cf3be49bdeb470f8a0", "http://filestoresg1.beetalkmobile.com:8081/file/22a788f63975f962eb26eeb37056ac34", "http://filestoresg1.beetalkmobile.com:8081/file/66e3ef341642a82627ab2dd1f98f7814"], "urls": [], "title": "\u5927\u9d6c\u7063\u62cd\u62cd"}, "threadStatus": 0, "regionId": 886, "barStatus": 0, "barId": 77, "postBy": {"utc": 1420975676000, "level": 32, "location": "Pingtung County\u00b7Taiwan", "avatar": "http://filestoresg1.beetalkmobile.com:8081/file/6501955414664151256", "name": "\u30de\u30f3\u30c8\u30a6_\u30ea"}, "id": 253434}
