{"forum": {"content": "\u5973\u4eba<br /><br />\u8981\u7576\u500b\u5e78\u798f\u7684\u5973\u4eba\ud83d\udc8b", "images": ["http://filestoresg1.beetalkmobile.com:8081/file/e10b5332db1af7f5e59d9c38e231cece"], "urls": [], "title": "\ud83d\ude46\u2764\ufe0f\ud83d\udc9a\ud83d\udc9c\ud83d\udc99\ud83d\udc9b"}, "threadStatus": 1, "regionId": 886, "barStatus": 0, "barId": 4, "postBy": {"utc": 1420975661000, "level": 13, "location": "\u53f0\u5317\u5e02\u00b7\u53f0\u7063", "avatar": "http://filestoresg1.beetalkmobile.com:8081/file/-9137305562855684341", "name": "\ud83d\udc97\u96c5\u96c5"}, "id": 253433}
