{"forum": {"content": "\u95a8\u623f\u60c5\u8da3\u61c9\u8a72\u4eba\u4eba\u6709\u5427<br /><br />\u554a\u4f60\u5011\u559c\u6b61\u5c0d\u53e6\u4e00\u534a\u8aaa\u4ec0\u9ebc\u6311\u9017\u6027\u7684\u8a71\uff1f<br />\u8aaa\u4f86\u807d\u807d\ud83d\ude0e", "images": ["http://filestoresg1.beetalkmobile.com:8081/file/661bb88acd20205d526bf6405d1de81e"], "urls": [], "title": "\u4f60\u6703\u8aaa\u4ec0\u9ebc"}, "threadStatus": 1, "regionId": 886, "barStatus": 2, "barId": 5, "postBy": {"utc": 1423889049000, "level": 9, "location": "\u9ad8\u96c4\u5e02\u00b7\u53f0\u7063", "avatar": "http://filestoresg1.beetalkmobile.com:8081/file/5798906792557623669", "name": "Avocado \ud83e\udd51"}, "id": 497476}
