{"forum": {"content": "\u5c0f\u6642\u5019\u8ddf\u73fe\u5728\u5dee\u597d\u591a\uff01\uff01", "images": ["http://filestoresg1.beetalkmobile.com:8081/file/ddf704f5df73b3ff00c40abf7aa59dfc", "http://filestoresg1.beetalkmobile.com:8081/file/f1eb6e2816d93ee39f84aca2c7c9a5ea"], "urls": [], "title": "\u5dee\u597d\u591a\uff1f"}, "threadStatus": 1, "regionId": 886, "barStatus": 0, "barId": 4, "postBy": {"utc": 1421074221000, "level": 0, "location": "\u9ad8\u96c4\u5e02\u00b7\u53f0\u7063", "avatar": "http://filestoresg1.beetalkmobile.com:8081/file/244668832872247092", "name": "\uc624\ube60"}, "id": 261562}
