{"forum": {"content": "\u5728\u9019\u8981\u51b7\u4e0d\u51b7\u7684\u5929\u6c23\uff0c\u5927\u8863\u539a\u5916\u5957\u66ab\u6642\u5fcd\u4f4f\uff0c\u9577\u896f\u886b\u52a0\u4e0a\u4e00\u4ef6\u5167\u642d\u8863\u5373\u53ef\u61c9\u4ed8\u3002<br />\u8272\u8abf\u5728\u4e0b\u534a\u8eab\u7528\u9ed1\u8272\u4fee\u98fe\u800c\u4e0a\u8eab\u7528\u9bae\u8c54\u85cd\u9ede\u4f5c\u51fa\u8ce3\u9ede!<br />shit:anges b,<br />tee: dickies<br />trouser: upset<br />shoes: planme", "images": ["http://filestoresg1.beetalkmobile.com:8081/file/6faeb5a71aeb448e9b611fdaeb2751f4"], "urls": [], "title": "\u7a7f\u642d\u9700\u8981\u4e0d\u65b7\u5b78\u7fd2\u3002"}, "threadStatus": 0, "regionId": 886, "barStatus": 0, "barId": 36, "postBy": {"utc": 1415603309000, "level": 6, "location": "\u65b0\u838a\u5340\u00b7\u53f0\u7063", "avatar": "http://filestoresg1.beetalkmobile.com:8081/file/-1590495240751122462", "name": "\u67e5\u723e\u65af"}, "id": 13386}
