{"forum": {"content": "\u6628\u5929\u525b\u6eff\u9031\u6b72\u55b2\uff01", "images": ["http://filestoresg1.beetalkmobile.com:8081/file/0c99c919d577496380f354c9d58e4549", "http://filestoresg1.beetalkmobile.com:8081/file/4c5abcd9c9656c25412e77cfc3f07eab", "http://filestoresg1.beetalkmobile.com:8081/file/833f07193dbd58c93358cd53e1c4b716", "http://filestoresg1.beetalkmobile.com:8081/file/2ebefd35e2e96cfc0b499129e58d3ff2"], "urls": [], "title": "\u6211\u5bb6\u5c0f\u9577\u5973"}, "threadStatus": 0, "regionId": 886, "barStatus": 0, "barId": 77, "postBy": {"utc": 1423139489000, "level": 7, "location": "\u65b0\u5317\u5e02\u00b7\u53f0\u7063", "avatar": "http://filestoresg1.beetalkmobile.com:8081/file/-7895933844995550834", "name": "\u311a\u51a0\u4ed4"}, "id": 428443}
