{"forum": {"content": "\u9019\u662f\u9023\u7e8c\u5047\u671f\u7b2c\u4e00\u5929\u5230\u6b66\u5dba\u6240\u62cd\u651d\u7684\u98a8\u666f<br />https://m.facebook.com/\u65c5\u884c\u8a18\u61b6-273630782760614/manager/?ref=bookmark<br />\u6211\u7684\u7c89\u5c08 \u65c5\u884c\u8a18\u61b6", "images": ["http://filestoresg1.beetalkmobile.com:8081/file/9299635c90182dedaf130dfd2b7a85e3", "http://filestoresg1.beetalkmobile.com:8081/file/3d892576685429bf3437248a95058bc6", "http://filestoresg1.beetalkmobile.com:8081/file/95501fb7e2162bbe4a59393a8538d937", "http://filestoresg1.beetalkmobile.com:8081/file/d5bfcc5bac5f7a2c65ca2882b07bc126", "http://filestoresg1.beetalkmobile.com:8081/file/db9a25b984be396293369cd857c90820"], "urls": [], "title": "[\u624b\u6a5f\u651d\u5f71]\u6b66\u5dba\u5206\u4eab"}, "threadStatus": 0, "regionId": 886, "barStatus": 0, "barId": 77, "postBy": {"utc": 1425190823000, "level": 2, "location": "\u53f0\u5357\u5e02\u00b7\u53f0\u7063", "avatar": "http://filestoresg1.beetalkmobile.com:8081/file/-1718583946455351385", "name": "J"}, "id": 634117}
