{"forum": {"content": "\u96a8\u4fbf", "images": ["http://filestoresg1.beetalkmobile.com:8081/file/5e592497d0fd368290c2d45fed02bb50", "http://filestoresg1.beetalkmobile.com:8081/file/b1c94f19c9a167c4f8aa82561cc0a01d", "http://filestoresg1.beetalkmobile.com:8081/file/4e86ee6acf8cc41568029e45938a65dd", "http://filestoresg1.beetalkmobile.com:8081/file/79f53f753baad6612a0f9f868e44fd4a", "http://filestoresg1.beetalkmobile.com:8081/file/d54534b137082e0f2daf2797a8b9d053", "http://filestoresg1.beetalkmobile.com:8081/file/e28b8de68978f04266ebfd4351cad10e"], "urls": [], "title": "\u7121\u984c"}, "threadStatus": 1, "regionId": 886, "barStatus": 0, "barId": 4, "postBy": {"utc": 1426309433000, "level": 1, "location": "\u53f0\u5357\u5e02\u00b7\u53f0\u7063", "avatar": "http://filestoresg1.beetalkmobile.com:8081/file/8638553901931097724", "name": "\u539f\u7121\u8272"}, "id": 753080}
