{"forum": {"content": "\u73fe\u5728\u8d8a\u4f86\u8d8a\u591a\u79c1\u5eda\u4e86\uff0c\u5728\u79c1\u5bc6\u7684\u74b0\u5883\u7528\u9910\uff0c\u611f\u89ba\u9084\u662f\u883b\u597d\u7684\uff0c\u8001\u95c6\u4e00\u6b21\u53ea\u62db\u5f85\u4e00\u7d44\u5ba2\u4eba\uff0c\u96d6\u7136\u5f88\u8cea\u7591\u9019\u6a23\u80fd\u5920\u7dad\u751f\u55ce\uff0c\u4f46\u662f\u5e0c\u671b\u597d\u7684\u6771\u897f\u80fd\u5920\u5e38\u5b58", "images": ["http://filestoresg1.beetalkmobile.com:8081/file/e43df254c00722b957404c7f185c7c0b", "http://filestoresg1.beetalkmobile.com:8081/file/178e30635a99a2a1688662fe7543b04c", "http://filestoresg1.beetalkmobile.com:8081/file/fb0adedbf1882f3c5e4ccfccf1393c17", "http://filestoresg1.beetalkmobile.com:8081/file/4d5b0caee1d0bcf0d29a949007330d35", "http://filestoresg1.beetalkmobile.com:8081/file/01d44144402fcd50a6360141a0ec2032", "http://filestoresg1.beetalkmobile.com:8081/file/9df6607761ac956e5f7e4359bc82a7ab"], "urls": [], "title": "\u79c1\u5eda"}, "threadStatus": 0, "regionId": 886, "barStatus": 0, "barId": 98, "postBy": {"utc": 1416709015000, "level": 3, "location": "", "avatar": "http://filestoresg1.beetalkmobile.com:8081/file/2643147890812894271", "name": "\u5c31\u662f\u611b\u4e82\u62cd"}, "id": 27096}
