{"forum": {"content": "\u4e0d\u9650\u8a71\u984c\uff0c\u96a8\u4fbf\u4e82\u804a\u2026\u2026", "images": ["http://filestoresg1.beetalkmobile.com:8081/file/5be4b7fd005e850a75c4f7f0ea2e1262"], "urls": [], "title": "\u627e\u4eba\u6253\u5c41\u804a\u5929\u2026\u2026"}, "threadStatus": 0, "regionId": 886, "barStatus": 0, "barId": 205, "postBy": {"utc": 1416737363000, "level": 10, "location": "\u9ad8\u96c4\u5e02\u00b7\u53f0\u7063", "avatar": "http://filestoresg1.beetalkmobile.com:8081/file/830947122575300297", "name": "\u4f0d\u58f9\u96f6"}, "id": 27529}
