{"forum": {"content": "\u53ef\u611b\u7684\u9ed1\u8cb4\u8cd3(\u256f\u0437\u2570)", "images": ["http://filestoresg1.beetalkmobile.com:8081/file/68ed06b7a18cf7be21bad7d6d58141a9", "http://filestoresg1.beetalkmobile.com:8081/file/b8776099f0c5f8df8a6db716d5a17d0c", "http://filestoresg1.beetalkmobile.com:8081/file/c2cb3abf5f0adfa9120c56bb5487258f", "http://filestoresg1.beetalkmobile.com:8081/file/8c900b33f4eeda84f4cba521e4534cd3", "http://filestoresg1.beetalkmobile.com:8081/file/568fd221919f0c8a7d3d8db188263009", "http://filestoresg1.beetalkmobile.com:8081/file/c2f0099dbece3d43acde23b52481f77c"], "urls": [], "title": "\u65b0\u5bf5\u5152(^\u03c9^)\u9ed1\u7cd6\u599e"}, "threadStatus": 0, "regionId": 886, "barStatus": 0, "barId": 105, "postBy": {"utc": 1421122674000, "level": 2, "location": "\u53f0\u5357\u5e02\u00b7\u53f0\u7063", "avatar": "http://filestoresg1.beetalkmobile.com:8081/file/-3045926478598027535", "name": "\u6e96\u5099\u8aaa\u63b0\u63b0"}, "id": 264673}
