{"forum": {"content": "\u8acb\u5404\u4f4d\u9818\u990a\u4ee3\u66ff\u8cfc\u8cb7\uff01<br />\u5c0a\u91cd\u5c0f\u751f\u547d\uff01<br />\u6b3a\u8ca0\u8c93\u72d7\u7684\u5c31\u5225\u8b93\u6211\u9047\u5230\uff01", "images": ["http://filestoresg1.beetalkmobile.com:8081/file/cc83eb62d77bec2521a043e54874af9f", "http://filestoresg1.beetalkmobile.com:8081/file/6b55f67079041abc6d195e90a2081d91", "http://filestoresg1.beetalkmobile.com:8081/file/b765cc315638d9acf79c7df3206bd6fe"], "urls": [], "title": "\u5c0a\u91cd\u751f\u547d."}, "threadStatus": 1, "regionId": 886, "barStatus": 0, "barId": 105, "postBy": {"utc": 1423156595000, "level": 6, "location": "", "avatar": "http://filestoresg1.beetalkmobile.com:8081/file/-8389258325651241727", "name": "08"}, "id": 430513}
