{"forum": {"content": "\u671f\u5f85\u4ea4\u5230\u5973\u53cb\u3001\u4e0d\u5584\u65bc\u8868\u9054\u7684\u6211\u662f\u5426\u53ef\u4ee5\u6253\u52d5\u4f60\u7684\u5fc3", "images": ["http://filestoresg1.beetalkmobile.com:8081/file/abcc0ce93524a7f5c6c585a7e6a60cd4"], "urls": [], "title": "\u671f\u5f85"}, "threadStatus": 0, "regionId": 886, "barStatus": 0, "barId": 205, "postBy": {"utc": 1425610157000, "level": 6, "location": "\u9ad8\u96c4\u5e02\u00b7\u53f0\u7063", "avatar": "http://filestoresg1.beetalkmobile.com:8081/file/4842021614535025981", "name": "\u8000"}, "id": 679052}
