{"forum": {"content": "\u4eca\u5929<br />\u5927\u5bb6\u90fd\u8981\u958b\u5fc3\u9762\u5c0d\u5537\uff01", "images": ["http://filestoresg1.beetalkmobile.com:8081/file/867d920ce8c4482046cf6193d7af240a", "http://filestoresg1.beetalkmobile.com:8081/file/e45f1cc606dfd48915a853aba9a71159", "http://filestoresg1.beetalkmobile.com:8081/file/cefd0bd6afa5adc04d1f8f76f3de304b", "http://filestoresg1.beetalkmobile.com:8081/file/e45ad10287f4705e1b9091ba4a04c311", "http://filestoresg1.beetalkmobile.com:8081/file/d9ee8b4a57f222eb044465247aeb7f07"], "urls": [], "title": "\u7acb\u6625"}, "threadStatus": 0, "regionId": 886, "barStatus": 0, "barId": 33, "postBy": {"utc": 1423040073000, "level": 3, "location": "\u6843\u5712\u5e02\u00b7\u53f0\u7063", "avatar": "http://filestoresg1.beetalkmobile.com:8081/file/-5893218496562551539", "name": "\u30ed\u30fc"}, "id": 420441}
