{"forum": {"content": "\u4f55\u6642\u624d\u80fd\u62dc\u5225\u55ae\u8eab\u3002\u3002\u3002\u3002\u3002", "images": ["http://filestoresg1.beetalkmobile.com:8081/file/5454188fccbf3fa4bc4810fcaed56e9f", "http://filestoresg1.beetalkmobile.com:8081/file/f53f2f4fe2c0f3e9827c91fbb5ba7dd5"], "urls": [], "title": "\u55ae\u8eab\u4e2d"}, "threadStatus": 1, "regionId": 886, "barStatus": 0, "barId": 205, "postBy": {"utc": 1418232747000, "level": 2, "location": "\u82d7\u6817\u7e23\u00b7\u53f0\u7063", "avatar": "http://filestoresg1.beetalkmobile.com:8081/file/4615098904879341737", "name": "\u5c0f\u6cb3\u00a9"}, "id": 59171}
