{"forum": {"content": "\u540c\u4e0a@@", "images": ["http://filestoresg1.beetalkmobile.com:8081/file/7882fc5aa92ba9d2fdeb14df5c73b742", "http://filestoresg1.beetalkmobile.com:8081/file/65ddc6ae018d0c224be5e65e71330229"], "urls": [], "title": "\u55ae\u8eab\u5341\u5e74\uff0c\u6c42\u8a8d\u990a(\u8aaa\u7b11\u7684\uff0c\u67d0\u8cc0\u7b11("}, "threadStatus": 0, "regionId": 886, "barStatus": 0, "barId": 205, "postBy": {"utc": 1421753953000, "level": 12, "location": "\u9ad8\u96c4\u5e02\u00b7\u53f0\u7063", "avatar": "http://filestoresg1.beetalkmobile.com:8081/file/-9104296025434634612", "name": "ONG ONG ONG"}, "id": 316980}
