{"forum": {"content": "\u559d\u9152 \u662f\u60f3\u628a\u5bc2\u5bde\u548c\u60b2\u50b7\u7d66\u6df9\u6c92\u22ef<br />\u53ea\u662f\u597d\u50cf \u5b83\u5011\u5b78\u6703\u4e86\u6e38\u6cf3\u22ef", "images": ["http://filestoresg1.beetalkmobile.com:8081/file/a1cc84c55f97a0a3ff580108c4ecc481"], "urls": [], "title": "\u6216\u8a31\u5c31\u9019\u6a23"}, "threadStatus": 1, "regionId": 886, "barStatus": 0, "barId": 205, "postBy": {"utc": 1421254687000, "level": 8, "location": "\u53f0\u5317\u5e02\u00b7\u53f0\u7063", "avatar": "http://filestoresg1.beetalkmobile.com:8081/file/6756579225042271491", "name": "\u840a\u6069"}, "id": 276666}
