{"forum": {"content": "\u611b\u60c5\u662f\u4ec0\u9ebc!\u591a\u6b21\u50b7\u75db\u904e\u8ab0\u6703\u9858\u610f\u771f\u5fc3\u5c0d\u5f85\u611b\u60c5", "images": ["http://filestoresg1.beetalkmobile.com:8081/file/ee888177b93a0398a55d52980f0bf0e7"], "urls": [], "title": "\u771f\u5fc3\u6c92\u6709\u7528!"}, "threadStatus": 0, "regionId": 886, "barStatus": 0, "barId": 383, "postBy": {"utc": 1423497118000, "level": 0, "location": "\u6843\u5712\u5e02\u00b7\u53f0\u7063", "avatar": "http://filestoresg1.beetalkmobile.com:8081/file/5054416331323855460", "name": "\u5713\u5713"}, "id": 459398}
