{"forum": {"content": "\u6211\u60f3\u627e\u500b\u53ef\u4ee5\u8ac7\u6200\u611b\u7684\u5c0d\u50cf\u5f88\u96e3\u55ce\uff1f\u518d\u4e0d\u7d50\u5a5a\u6211\u88ab\u5a01\u8105\u8981\u5a36\u5916\u914d\u4e86", "images": ["http://filestoresg1.beetalkmobile.com:8081/file/58419e418c0e7ea41c1464d82fcf0678", "http://filestoresg1.beetalkmobile.com:8081/file/82ed111ad0fc6f114bfe3ac669756e5d", "http://filestoresg1.beetalkmobile.com:8081/file/d843e03aad6f4414fc64fa48982b197c", "http://filestoresg1.beetalkmobile.com:8081/file/81abf1bd470a8c30f2a992053b1678a9", "http://filestoresg1.beetalkmobile.com:8081/file/b7ddcbcd0dc2577717405ae0218a8252", "http://filestoresg1.beetalkmobile.com:8081/file/27e422af5ab879b4fdc0128b86d19360"], "urls": [], "title": "\u8ab0\u662f\u6211\u7684\u771f\u547d\u5929\u5973"}, "threadStatus": 0, "regionId": 886, "barStatus": 0, "barId": 205, "postBy": {"utc": 1426982385000, "level": 1, "location": "\u9ad8\u96c4\u5e02\u00b7\u53f0\u7063", "avatar": "http://filestoresg1.beetalkmobile.com:8081/file/-255799172862417128", "name": "\u8523\u54e5"}, "id": 821563}
