{"forum": {"content": "\u770b\u8457\u670b\u53cb\u5e78\u798f\uff0c\u5fc3\u4e2d\u7e3d\u662f\u4e5f\u4e9b\u7fa8\u6155<br />\u4f46\u80cc\u5f8c\u7684\u5fc3\u9178\uff0c\u6211\u53ef\u4e0d\u6562\u606d\u7dad\u3002<br />\u7576\u5225\u4eba\u5c0f\u4e09\uff0c\u6211\u8fa6\u4e0d\u5230\u3002<br />\u56e0\u70ba\u6211\u59cb\u7d42\u8a8d\u70ba\u600e\u6a23\u5f97\u5230\u5c31\u6703\u600e\u6a23\u5931\u53bb\uff0c<br />\u4e0d\u53bb\u6436\uff0c\u4e5f\u4e0d\u59d4\u5c48\u8b93\u81ea\u5df1\u505a\u7b2c\u4e09\u8005\u3002<br />\u4f60\u5011\u8aaa\u662f\u4e0d\u662f\u5462\u256e(\u256f_\u2570)\u256d", "images": ["http://filestoresg1.beetalkmobile.com:8081/file/f75adb89623c863f0dda20cccfe85f69"], "urls": [], "title": "\u662f\u4e0d\u662f"}, "threadStatus": 0, "regionId": 886, "barStatus": 0, "barId": 205, "postBy": {"utc": 1418891570000, "level": 6, "location": "\u65b0\u7af9\u5e02\u00b7\u53f0\u7063", "avatar": "http://filestoresg1.beetalkmobile.com:8081/file/-8537706686835615534", "name": "\u9ed1\u6735\u8f9b"}, "id": 103101}
