{"forum": {"content": "\u6709\u591a\u5c11\u611b\u53ef\u4ee5\u91cd\u4f86<br />\u6709\u591a\u5c11\u4eba\u9858\u610f\u7b49\u5f85<br />\u7576\u61c2\u5f97\u73cd\u60dc\u4ee5\u5f8c\u56de\u4f86<br />\u537b\u4e0d\u77e5\u90a3\u4efd\u611b\u6703\u4e0d\u6703\u9084\u5728<br />\u5982\u679c\u9084\u53ef\u4ee5\u5728\u91cd\u4f86\u6211\u6703\u66f4\u52a0\u73cd\u60dc\u59b3\uff01", "images": ["http://filestoresg1.beetalkmobile.com:8081/file/bc14cb833a46366c754fd5c2577b7459", "http://filestoresg1.beetalkmobile.com:8081/file/376a8a706fa8ec7c8797a66aef969a69", "http://filestoresg1.beetalkmobile.com:8081/file/0b4311975ea46e3cb09b0acd69abe9ed"], "urls": [], "title": "\u9084\u80fd\u4e0d\u80fd\u56de\u5230\u904e\u53bb"}, "threadStatus": 0, "regionId": 886, "barStatus": 0, "barId": 15, "postBy": {"utc": 1414797676000, "level": 1, "location": "\u524d\u91d1\u5340\u00b7\u53f0\u7063", "avatar": "http://filestoresg1.beetalkmobile.com:8081/file/-3524207227101928931", "name": "\u8ed2\u777f"}, "id": 4795}
