{"forum": {"content": "\u5e0c\u671b\u5927\u5bb6\u90fd\u80fd\u958b\u5fc3\u5537\u2265\ufe4f\u2264\uff01\uff01\uff01<br />\u6700\u5f8c\u4e00\u5f35\u54c1\u5617\u7f8e\u98df\u56c9\uff01\uff01\uff01", "images": ["http://filestoresg1.beetalkmobile.com:8081/file/71a7ae9031369201dd113bf6d3682c7e", "http://filestoresg1.beetalkmobile.com:8081/file/8894c677ec179191ba395de0eb7ec7c1", "http://filestoresg1.beetalkmobile.com:8081/file/fc54b5b15dd2cd970b1a4689111fe3c2", "http://filestoresg1.beetalkmobile.com:8081/file/595c140ae76ef4cec91183bfbb3b736c", "http://filestoresg1.beetalkmobile.com:8081/file/246ab5dccc05b5f73fe557dbb908592a"], "urls": [], "title": "\u770b\u5927\u5bb6PO\u2026\u6211\u4e5fPo\u4e00\u4e0b~"}, "threadStatus": 0, "regionId": 886, "barStatus": 0, "barId": 4, "postBy": {"utc": 1415526849000, "level": 2, "location": "Taiwan", "avatar": "http://filestoresg1.beetalkmobile.com:8081/file/-6023280826222313555", "name": "Elsa"}, "id": 12401}
