{"forum": {"content": "\u5c0f\u9ad8\u4e00<br />16\u6b72<br />\u54c8\u54c8\u54c8\u54c8\u54c8<br />\u4f60\u5011\u53ef\u4ee5\u7d66\u6211\u8a8d\u8b58\u54a9", "images": ["http://filestoresg1.beetalkmobile.com:8081/file/083d210c7e42d48742b3064b4b81f5b2", "http://filestoresg1.beetalkmobile.com:8081/file/ef054817579aaefec2b7cbc75357988f", "http://filestoresg1.beetalkmobile.com:8081/file/7a1d8bbcbc179dc35b89162ee7b000f0", "http://filestoresg1.beetalkmobile.com:8081/file/5ea6854840c9af2f18d2ef61a496a699", "http://filestoresg1.beetalkmobile.com:8081/file/4470fc815cb15f08ef5339188805b7fe", "http://filestoresg1.beetalkmobile.com:8081/file/34f7fa740e8a8d1ba9a761c102d5ead5"], "urls": [], "title": "\u5c0f\u9ad8\u4e00"}, "threadStatus": 1, "regionId": 886, "barStatus": 0, "barId": 438, "postBy": {"utc": 1428812466000, "level": 1, "location": "\u6843\u5712\u5e02\u00b7\u53f0\u7063", "avatar": "http://filestoresg1.beetalkmobile.com:8081/file/-8856654116703442423", "name": "185"}, "id": 999992}
