{"forum": {"content": "\u8003\u5012\u6211\u4e86  \u600e\u6a23\u624d\u7b97\u54ac\u5507\u599d= =||||  \u6f38\u5c64\u7684\u610f\u601d\uff1f", "images": ["http://filestoresg1.beetalkmobile.com:8081/file/37def659f223763052126b6954ca900f", "http://filestoresg1.beetalkmobile.com:8081/file/cf0b76047247b73c56b6f74a98c3db66"], "urls": [], "title": "\u54ac\u5507\u599d\uff1f\u54ac\u8822\u599d\uff1f\uff01"}, "threadStatus": 0, "regionId": 886, "barStatus": 0, "barId": 4, "postBy": {"utc": 1420807060000, "level": 9, "location": "\u53f0\u4e2d\u5e02\u00b7\u53f0\u7063", "avatar": "http://filestoresg1.beetalkmobile.com:8081/file/1343159007715382053", "name": "\ud83d\udc40\u5927\u773c\ud83d\udc40"}, "id": 239978}
