{"forum": {"content": "\u5927\u5bb6\u597d\u6211\u53eb\u6c5f\u96e8\u840c", "images": ["http://filestoresg1.beetalkmobile.com:8081/file/ce6178bafa6105fff5f082862c584cb4", "http://filestoresg1.beetalkmobile.com:8081/file/2eaeffe2cadf9039a5b018228be6a859", "http://filestoresg1.beetalkmobile.com:8081/file/29edf8c6e1df7d76baa255a433b6f208", "http://filestoresg1.beetalkmobile.com:8081/file/5bef71c7546cdaf4557b00fea4fce818", "http://filestoresg1.beetalkmobile.com:8081/file/c719e608d9a0b1c127c52f9591834b34"], "urls": [], "title": "\u840c\u840c"}, "threadStatus": 1, "regionId": 886, "barStatus": 0, "barId": 105, "postBy": {"utc": 1414973287000, "level": 1, "location": "", "avatar": "http://filestoresg1.beetalkmobile.com:8081/file/1216932873817402882", "name": "\u3002"}, "id": 6085}
