{"forum": {"content": "\u6709\u96f2\u6797\u5973\u5b69\u9084\u6c92\u7761\u7684\u55ce", "images": ["http://filestoresg1.beetalkmobile.com:8081/file/1d766bf2c3e5e527a0d0de38c3ce215e"], "urls": [], "title": "Cherche  \u96f2\u6797\u5973\u5b69"}, "threadStatus": 1, "regionId": 886, "barStatus": 2, "barId": 5, "postBy": {"utc": 1424803365000, "level": 2, "location": "\u96f2\u6797\u7e23\u00b7\u53f0\u7063", "avatar": "http://filestoresg1.beetalkmobile.com:8081/file/-5411237672201226752", "name": "\u9ea5\u514b"}, "id": 592269}
