{"forum": {"content": "\u5154\u5b50\u662f\u82b1\u82b1\u3002\u3002\u72d7\u5152\u662f\u9322\u9322\uff01<br /><br />^^", "images": ["http://filestoresg1.beetalkmobile.com:8081/file/c2926a3e6247eae8240cdb52f8c2d724", "http://filestoresg1.beetalkmobile.com:8081/file/6e8561b74fd18a4d5997b78b5e033d12", "http://filestoresg1.beetalkmobile.com:8081/file/ab70563a174fcf306fc2c76bca0d08cc"], "urls": [], "title": "\u82b1\u9322\u4e8c\u4eba\u7d44"}, "threadStatus": 0, "regionId": 886, "barStatus": 0, "barId": 105, "postBy": {"utc": 1417419465000, "level": 2, "location": "\u5f70\u5316\u7e23\u00b7\u53f0\u7063", "avatar": "http://filestoresg1.beetalkmobile.com:8081/file/-7142305484165252904", "name": "\u6bd4\u718a"}, "id": 36974}
