{"forum": {"content": "\u4e0a\u4e2a\u6708\u4e70\u4e86converse\u65e5\u672c\u9650\u5b9a\u6b3e\u7684\u978b\u5b50<br />\u53ef\u662f\u4e70\u4e86\u4e4b\u540e\u4e0d\u77e5\u8be5\u600e\u4e48\u642d\u914d<br />\u5168\u8eab\u90fd\u6df1\u8272<br />\u978b\u5b50\u7c73\u9ec4<br />\u611f\u89c9\u597d\u602a<br />\u60f3\u8bf4\u914d\u6c34\u624b\u670d<br />\u53ef\u53c8\u4e0d\u597d\u914d<br />\u6709\u4eba\u53ef\u4ee5\u7ed9\u70b9\u610f\u89c1\u561b><", "images": ["http://filestoresg1.beetalkmobile.com:8081/file/b9ed0cf7a03e34383bca75fa97c90968"], "urls": [], "title": "converse\u65e5\u672c\u9650\u5b9a\u6b3e"}, "threadStatus": 1, "regionId": 886, "barStatus": 0, "barId": 36, "postBy": {"utc": 1423912432000, "level": 3, "location": "\u57fa\u9686\u5e02\u00b7\u53f0\u7063", "avatar": "http://filestoresg1.beetalkmobile.com:8081/file/-3140714280386220059", "name": "\u5bf6\u5bf6\u2764  "}, "id": 499882}
