{"forum": {"content": "\u570b\u270c\u751f\u5537.<br />\u6b61\u8fce\u4f60\u4f86\u8a8d\u8b58\u6211.\ud83d\ude01<br />\u5feb\u4f86\u8ffd\u8e64\u6211\u7684ig:LOVE0124543", "images": ["http://filestoresg1.beetalkmobile.com:8081/file/b142500e39beafcddecb43573342176a"], "urls": [], "title": "\u55e8 \u4f60\u597d\u2728"}, "threadStatus": 1, "regionId": 886, "barStatus": 0, "barId": 512, "postBy": {"utc": 1423682134000, "level": 3, "location": "\u65b0\u5317\u5e02\u00b7\u53f0\u7063", "avatar": "http://filestoresg1.beetalkmobile.com:8081/file/1370465378614895126", "name": "\u3002"}, "id": 477579}
