{"forum": {"content": "\u64e0\u5976\uff0c\u9732\u5976\uff0c\u561f\u5634\uff0c<br />\u88dd\u53ef\u611b\u7684\uff0c\u770b\u81a9\u4e86<br />\u4f86\u6bd4\u8cfd\u9b3c\u81c9\u597d\u55ce\uff1f", "images": ["http://filestoresg1.beetalkmobile.com:8081/file/0160dea9508ec8f43fa1bab48b8885d0"], "urls": [], "title": "\u4f86\u6bd4\u8cfd\u9b3c\u81c9\u597d\u55ce\uff1f"}, "threadStatus": 1, "regionId": 886, "barStatus": 0, "barId": 4, "postBy": {"utc": 1427778465000, "level": 3, "location": "Taoyuan City\u00b7Taiwan", "avatar": "http://filestoresg1.beetalkmobile.com:8081/file/-570702606903378756", "name": "\u6211\u5728\u54ea"}, "id": 901289}
