{"forum": {"content": "\u55e8\u55e8 \ud83d\ude0a\u570b\u4e8c\u311b\ud83d\ude0f\u81fa\u4e2d\u4eba", "images": ["http://filestoresg1.beetalkmobile.com:8081/file/10255a3d816069989ade833819090507", "http://filestoresg1.beetalkmobile.com:8081/file/8ff2c6ad0753a7a38d311286a663114f", "http://filestoresg1.beetalkmobile.com:8081/file/b0f2fa9e53bb20d42e8306d8994586ad"], "urls": [], "title": "\u563f\u270c"}, "threadStatus": 0, "regionId": 886, "barStatus": 0, "barId": 512, "postBy": {"utc": 1427033556000, "level": 2, "location": "Taichung City\u00b7Taiwan", "avatar": "http://filestoresg1.beetalkmobile.com:8081/file/7673366307587465265", "name": " \ud83d\ude0d\u73a5\u73a5.\ud83d\ude0d"}, "id": 827583}
