{"forum": {"content": "\u8acb\u554f\u9019\u53f0\u8eca\u8a55\u50f9\u5982\u4f55 \u5982\u679c\u8981\u8ce3 \u4ed6\u9084\u6709\u50f9\u55ce\uff1f\uff1f\uff1f", "images": ["http://filestoresg1.beetalkmobile.com:8081/file/ac9512d75593b6d83dc8961baaa71702"], "urls": [], "title": "Honda Prelude Si 4WS | Hemmings Daily"}, "threadStatus": 0, "regionId": 886, "barStatus": 0, "barId": 73, "postBy": {"utc": 1423065772000, "level": 2, "location": "\u65b0\u7af9\u7e23\u00b7\u53f0\u7063", "avatar": "http://filestoresg1.beetalkmobile.com:8081/file/9107094285382657026", "name": "\u80d6\u864e \ud83d\udc2f"}, "id": 423189}
