{"forum": {"content": "\u9019\u88e1\u662f\u54ea\u88e1", "images": ["http://filestoresg1.beetalkmobile.com:8081/file/e8acb0e8e64bf7f2c6f5b6e65d9fe604"], "urls": [], "title": "\u311c\u311c\u311c"}, "threadStatus": 0, "regionId": 886, "barStatus": 0, "barId": 4, "postBy": {"utc": 1421526673000, "level": 3, "location": "\u53f0\u5317\u5e02\u00b7\u53f0\u7063", "avatar": "http://filestoresg1.beetalkmobile.com:8081/file/1206953707736638691", "name": "\u62ce\ud83d\ude1d\u51b7\u6de1\u738b"}, "id": 299039}
