{"forum": {"content": "\u6211\u53ea\u6709\u9019\u5e7e\u5f35\u80fd\u770b\u4e86\u628a\uff0c\u62dc\u8a17\u4e0d\u8981\u5acc\u68c4\u6211", "images": ["http://filestoresg1.beetalkmobile.com:8081/file/d4d86dd68c1ff36d4fde4fa881327c74", "http://filestoresg1.beetalkmobile.com:8081/file/b371b75687904f524ac7df70e1023276", "http://filestoresg1.beetalkmobile.com:8081/file/bb326149159c13094ed3aafb496de4d6"], "urls": [], "title": "\u6211\u53ea\u6709\u9019\u5f35\u80fd\u770b\u4e86\u628a"}, "threadStatus": 1, "regionId": 886, "barStatus": 0, "barId": 33, "postBy": {"utc": 1418800527000, "level": 2, "location": "\u6843\u5712\u7e23\u00b7\u53f0\u7063", "avatar": "http://filestoresg1.beetalkmobile.com:8081/file/-242790858054785279", "name": "\u6162\u9748\u9b42"}, "id": 97154}
